ecr/__init__.py
ecr/__main__.py
ecr/core/__init__.py
ecr/core/manager.py
ecr/ui/__init__.py
ecr/ui/cli.py
ecr/ui/color.py
test/__init__.py
test/__main__.py
test/unit/__init__.py
edl_cr-0.0.1.1.dist-info/LICENSE
edl_cr-0.0.1.1.dist-info/METADATA
edl_cr-0.0.1.1.dist-info/WHEEL
edl_cr-0.0.1.1.dist-info/entry_points.txt
edl_cr-0.0.1.1.dist-info/top_level.txt
edl_cr-0.0.1.1.dist-info/RECORD
