Metadata-Version: 2.1
Name: edl-cr
Version: 0.0.1.1
Summary: A CLI tool to run code
Home-page: https://github.com/eXceediDeaL/edl-coderunner
Author: eXceed-iDeaL
Author-email: exceedideal@163.com
License: Apache-2.0
Project-URL: Bug Tracker, https://github.com/eXceediDeaL/edl-coderunner/issues
Project-URL: Documentation, https://github.com/eXceediDeaL/edl-coderunner/wiki
Project-URL: Source Code, https://github.com/eXceediDeaL/edl-coderunner
Keywords: code runner
Platform: UNKNOWN
Classifier: Development Status :: 2 - Pre-Alpha
Classifier: Programming Language :: Python :: 3.7
Classifier: License :: OSI Approved :: Apache Software License
Requires-Python: >=3.7
